obp_python/__init__.py
obp_python/api_client.py
obp_python/configuration.py
obp_python/rest.py
obp_python/api/__init__.py
obp_python/api/_covid_api_days_api.py
obp_python/api/_customer_cars_api.py
obp_python/api/_d_entity1_gh_29_uk_api.py
obp_python/api/_fish_port_api.py
obp_python/api/_foo_bar_api.py
obp_python/api/_insurance_policy_gh_29_uk_api.py
obp_python/api/_insurance_premium_gh_29_uk_api.py
obp_python/api/_march_hare_gh_29_uk_api.py
obp_python/api/_obp_activity_obp_testing_01_api.py
obp_python/api/_odometer_gh_29_uk_api.py
obp_python/api/_simon_covid_api.py
obp_python/api/_sustrans_api.py
obp_python/api/_test1_api.py
obp_python/api/_test_daniel707_api.py
obp_python/api/account_access_api.py
obp_python/api/account_api.py
obp_python/api/account_application_api.py
obp_python/api/account_firehose_api.py
obp_python/api/account_information_service__ais_api.py
obp_python/api/account_metadata_api.py
obp_python/api/account_public_api.py
obp_python/api/aggregate_metrics_api.py
obp_python/api/api_api.py
obp_python/api/api_collection_api.py
obp_python/api/atm_api.py
obp_python/api/authentication_type_validation_api.py
obp_python/api/bank_accounts__dynamic_endpoint_api.py
obp_python/api/bank_api.py
obp_python/api/branch_api.py
obp_python/api/card_api.py
obp_python/api/confirmation_of_funds_service__piis_api.py
obp_python/api/connector_method_api.py
obp_python/api/consent_api.py
obp_python/api/consumer_api.py
obp_python/api/counterparty_api.py
obp_python/api/counterparty_metadata_api.py
obp_python/api/customer_api.py
obp_python/api/customer_meeting_api.py
obp_python/api/customer_message_api.py
obp_python/api/d_auth_api.py
obp_python/api/data_warehouse_api.py
obp_python/api/direct_debit_api.py
obp_python/api/documentation_api.py
obp_python/api/dynamic_api.py
obp_python/api/dynamic_endpoint_api.py
obp_python/api/dynamic_endpoint_manage_api.py
obp_python/api/dynamic_entity_api.py
obp_python/api/dynamic_entity_manage_api.py
obp_python/api/dynamic_message_doc_api.py
obp_python_apiv5.1-0.0.7.dist-info/METADATA
obp_python_apiv5.1-0.0.7.dist-info/WHEEL
obp_python_apiv5.1-0.0.7.dist-info/top_level.txt
obp_python_apiv5.1-0.0.7.dist-info/RECORD
