Metadata-Version: 2.1
Name: obp-python-apiv5.1
Version: 0.0.7
Summary: Open Bank Project API
Home-page: https://github.com/tawoe/obp-python
Author-email: contact@tesobe.com
Keywords: Swagger,Open Bank Project API
Requires-Dist: certifi >=2017.4.17
Requires-Dist: python-dateutil >=2.1
Requires-Dist: six >=1.10
Requires-Dist: urllib3 >=1.23
